awscon/__init__.py
awscon/awscon.py
awscon-0.0.13.dist-info/LICENSE
awscon-0.0.13.dist-info/METADATA
awscon-0.0.13.dist-info/WHEEL
awscon-0.0.13.dist-info/entry_points.txt
awscon-0.0.13.dist-info/top_level.txt
awscon-0.0.13.dist-info/RECORD
