Metadata-Version: 2.1
Name: awscon
Version: 0.0.13
Summary: Wrapper that displays all available EC2 instances and launchs an SSM console session for the selected one
Home-page: https://www.github.com/sergiopena/awscon
Author: Sergio Pena
Author-email: isergiopena@gmail.com
License: BSD
Keywords: aws ec2 ssm console ssh
Platform: UNKNOWN
Classifier: Development Status :: 3 - Alpha
Classifier: Topic :: Utilities
Classifier: License :: OSI Approved :: BSD License
Requires-Dist: boto3 (>=1.9.154)
Requires-Dist: botocore (>=1.12.154)
Requires-Dist: pyfzf
